Homework1_CLI_Search/__init__.py
Homework1_CLI_Search/searcher.py
ishutin_otus_homework1_cli_searcher-0.1.dist-info/METADATA
ishutin_otus_homework1_cli_searcher-0.1.dist-info/WHEEL
ishutin_otus_homework1_cli_searcher-0.1.dist-info/entry_points.txt
ishutin_otus_homework1_cli_searcher-0.1.dist-info/top_level.txt
ishutin_otus_homework1_cli_searcher-0.1.dist-info/RECORD
